{"v":"5.6.9","fr":25,"ip":0,"op":200,"w":200,"h":200,"nm":"S","ddd":0,"assets":[],"layers":[{"ddd":0,"ind":1,"ty":4,"nm":"s Outlines","sr":1,"ks":{"o":{"a":1,"k":[{"i":{"x":[0.833],"y":[0.833]},"o":{"x":[0.167],"y":[0.167]},"t":173,"s":[100]},{"t":199,"s":[0]}],"ix":11},"r":{"a":0,"k":0,"ix":10},"p":{"a":0,"k":[98.96,100,0],"ix":2,"x":"var $bm_rt;\nvar p = 0.81;\nvar a = 50;\nvar s = 1.70158;\nfunction easeandwizz_inOutExpo(t, b, c, d) {\n    if (t == 0)\n        return b;\n    if (t == d)\n        return $bm_sum(b, c);\n    if ((t /= d / 2) < 1)\n        return $bm_sum($bm_mul($bm_div(c, 2), Math.pow(2, $bm_mul(10, $bm_sub(t, 1)))), b);\n    return $bm_sum($bm_mul($bm_div(c, 2), $bm_sum($bm_neg(Math.pow(2, $bm_mul(-10, --t))), 2)), b);\n}\nfunction easeAndWizz() {\n    var t, d, sX, eX, sY, eY, sZ, eZ, val1, val2, val2, val3;\n    var n = 0;\n    if (numKeys > 0) {\n        n = nearestKey(time).index;\n        if (key(n).time > time) {\n            n--;\n        }\n    }\n    try {\n        var key1 = key(n);\n        var key2 = key($bm_sum(n, 1));\n    } catch (e) {\n        return null;\n    }\n    var dim = 1;\n    try {\n        key(1)[1].length;\n        dim = 2;\n        key(1)[2].length;\n        dim = 3;\n    } catch (e) {\n    }\n    t = $bm_sub(time, key1.time);\n    d = $bm_sub(key2.time, key1.time);\n    sX = key1[0];\n    eX = $bm_sub(key2[0], key1[0]);\n    if (dim >= 2) {\n        sY = key1[1];\n        eY = $bm_sub(key2[1], key1[1]);\n        if (dim >= 3) {\n            sZ = key1[2];\n            eZ = $bm_sub(key2[2], key1[2]);\n        }\n    }\n    if (time < key1.time || time > key2.time) {\n        return value;\n    } else {\n        val1 = easeandwizz_inOutExpo(t, sX, eX, d, a, p, s);\n        switch (dim) {\n        case 1:\n            return val1;\n            break;\n        case 2:\n            val2 = easeandwizz_inOutExpo(t, sY, eY, d, a, p, s);\n            return [\n                val1,\n                val2\n            ];\n            break;\n        case 3:\n            val2 = easeandwizz_inOutExpo(t, sY, eY, d, a, p, s);\n            val3 = easeandwizz_inOutExpo(t, sZ, eZ, d, a, p, s);\n            return [\n                val1,\n                val2,\n                val3\n            ];\n            break;\n        default:\n            return null;\n        }\n    }\n}\n$bm_rt = easeAndWizz() || value;"},"a":{"a":0,"k":[0.655,-92.482,0],"ix":1},"s":{"a":0,"k":[61.766,61.766,100],"ix":6,"x":"var $bm_rt;\nvar p = 0.81;\nvar a = 50;\nvar s = 1.70158;\nfunction easeandwizz_inOutExpo(t, b, c, d) {\n    if (t == 0)\n        return b;\n    if (t == d)\n        return $bm_sum(b, c);\n    if ((t /= d / 2) < 1)\n        return $bm_sum($bm_mul($bm_div(c, 2), Math.pow(2, $bm_mul(10, $bm_sub(t, 1)))), b);\n    return $bm_sum($bm_mul($bm_div(c, 2), $bm_sum($bm_neg(Math.pow(2, $bm_mul(-10, --t))), 2)), b);\n}\nfunction easeAndWizz() {\n    var t, d, sX, eX, sY, eY, sZ, eZ, val1, val2, val2, val3;\n    var n = 0;\n    if (numKeys > 0) {\n        n = nearestKey(time).index;\n        if (key(n).time > time) {\n            n--;\n        }\n    }\n    try {\n        var key1 = key(n);\n        var key2 = key($bm_sum(n, 1));\n    } catch (e) {\n        return null;\n    }\n    var dim = 1;\n    try {\n        key(1)[1].length;\n        dim = 2;\n        key(1)[2].length;\n        dim = 3;\n    } catch (e) {\n    }\n    t = $bm_sub(time, key1.time);\n    d = $bm_sub(key2.time, key1.time);\n    sX = key1[0];\n    eX = $bm_sub(key2[0], key1[0]);\n    if (dim >= 2) {\n        sY = key1[1];\n        eY = $bm_sub(key2[1], key1[1]);\n        if (dim >= 3) {\n            sZ = key1[2];\n            eZ = $bm_sub(key2[2], key1[2]);\n        }\n    }\n    if (time < key1.time || time > key2.time) {\n        return value;\n    } else {\n        val1 = easeandwizz_inOutExpo(t, sX, eX, d, a, p, s);\n        switch (dim) {\n        case 1:\n            return val1;\n            break;\n        case 2:\n            val2 = easeandwizz_inOutExpo(t, sY, eY, d, a, p, s);\n            return [\n                val1,\n                val2\n            ];\n            break;\n        case 3:\n            val2 = easeandwizz_inOutExpo(t, sY, eY, d, a, p, s);\n            val3 = easeandwizz_inOutExpo(t, sZ, eZ, d, a, p, s);\n            return [\n                val1,\n                val2,\n                val3\n            ];\n            break;\n        default:\n            return null;\n        }\n    }\n}\n$bm_rt = easeAndWizz() || value;"}},"ao":0,"shapes":[{"ty":"gr","it":[{"ind":0,"ty":"sh","ix":1,"ks":{"a":0,"k":{"i":[[0,0.044],[-1.145,-5.777],[-3.565,-6.239],[-5.666,-4.529],[-8.784,-2.627],[-11.203,0],[-14.663,11.849],[0,21.065],[8.021,9.158],[17.579,4.944],[6.002,1.385],[2.846,0.844],[0,9.28],[-3.726,3.074],[-6.084,0],[-0.374,-16.58],[0,0],[13.158,10.972],[23.873,0],[13.515,-11.156],[0,-17.012],[-7.235,-9.52],[-14.73,-5.061],[-16.907,-4.336],[-3.182,-3.074],[0,-5.663],[4.646,-3.132],[7.127,0],[0,15.461],[0,0]],"o":[[0,6.569],[1.4,6.832],[3.565,6.239],[5.663,4.532],[8.784,2.624],[21.766,0],[14.663,-11.849],[0,-17.474],[-8.021,-9.158],[-3.723,-0.964],[-6.005,-1.385],[-12.01,-3.132],[0,-4.941],[3.723,-3.074],[15.145,0],[0,0],[-0.137,-21.194],[-13.158,-10.969],[-21.01,0],[-13.517,11.159],[0,14.943],[7.235,9.52],[4.354,1.566],[7.381,1.809],[3.182,3.074],[0,5.546],[-4.646,3.132],[-16.121,0],[0,0],[0,-0.044]],"v":[[-73.309,-56.334],[-71.59,-37.817],[-64.145,-18.212],[-50.3,-2.059],[-28.63,8.679],[1.347,12.618],[55.99,-5.154],[77.984,-54.525],[65.951,-94.475],[27.549,-115.628],[12.962,-119.152],[-0.316,-122.498],[-18.327,-141.117],[-12.74,-153.139],[1.969,-157.75],[25.247,-132.877],[77.984,-132.877],[58.041,-181.126],[2.493,-197.583],[-49.295,-180.845],[-69.568,-138.587],[-58.716,-101.889],[-25.767,-80.014],[6.122,-71.157],[21.968,-63.835],[26.743,-50.729],[19.774,-37.711],[2.113,-33.013],[-22.067,-56.202],[-73.309,-56.202]],"c":true},"ix":2},"nm":"s","mn":"ADBE Vector Shape - Group","hd":false},{"ty":"st","c":{"a":0,"k":[0,0,0,1],"ix":3},"o":{"a":1,"k":[{"i":{"x":[0.833],"y":[0.833]},"o":{"x":[0.167],"y":[0.167]},"t":67,"s":[100]},{"t":83,"s":[0]}],"ix":4},"w":{"a":0,"k":2,"ix":5},"lc":1,"lj":1,"ml":4,"bm":0,"d":[{"n":"d","nm":"dash","v":{"a":0,"k":4,"ix":1}},{"n":"o","nm":"offset","v":{"a":0,"k":0,"ix":7}}],"nm":"Stroke 1","mn":"ADBE Vector Graphic - Stroke","hd":false},{"ty":"fl","c":{"a":0,"k":[0,0,0,1],"ix":4},"o":{"a":1,"k":[{"i":{"x":[0.833],"y":[0.833]},"o":{"x":[0.167],"y":[0.167]},"t":61,"s":[0]},{"t":81,"s":[100]}],"ix":5},"r":1,"bm":0,"nm":"Fill 1","mn":"ADBE Vector Graphic - Fill","hd":false},{"ty":"tr","p":{"a":0,"k":[0,0],"ix":2},"a":{"a":0,"k":[0,0],"ix":1},"s":{"a":0,"k":[100,100],"ix":3},"r":{"a":0,"k":0,"ix":6},"o":{"a":0,"k":100,"ix":7},"sk":{"a":0,"k":0,"ix":4},"sa":{"a":0,"k":0,"ix":5},"nm":"Transform"}],"nm":"s","np":3,"cix":2,"bm":0,"ix":1,"mn":"ADBE Vector Group","hd":false},{"ty":"tm","s":{"a":0,"k":0,"ix":1},"e":{"a":1,"k":[{"i":{"x":[0.833],"y":[0.833]},"o":{"x":[0.167],"y":[0.167]},"t":0,"s":[0]},{"t":56,"s":[100]}],"ix":2},"o":{"a":0,"k":0,"ix":3},"m":1,"ix":2,"nm":"Trim Paths 1","mn":"ADBE Vector Filter - Trim","hd":false}],"ip":0,"op":200,"st":0,"bm":0}],"markers":[]}